ngocuyen/__init__.py
ngocuyen/main.py
ngocuyen-0.1.0.dist-info/LICENSE
ngocuyen-0.1.0.dist-info/METADATA
ngocuyen-0.1.0.dist-info/WHEEL
ngocuyen-0.1.0.dist-info/entry_points.txt
ngocuyen-0.1.0.dist-info/top_level.txt
ngocuyen-0.1.0.dist-info/RECORD
