Metadata-Version: 2.1
Name: ngocuyen
Version: 0.1.0
Summary: Python 3.x source code obfuscator for hiding and protecting production code.
Home-page: https://google.com
Author: huynhngocuyen
Author-email: linhngoc9601@gmail.com
License: AGPL-3.0
Platform: UNKNOWN
Requires-Python: >=3.6
License-File: LICENSE
Requires-Dist: colorama
